Core/Framework.py
Core/SAP.py
Core/Utilities.py
Core/__init__.py
Flow/Actions.py
Flow/Data.py
Flow/Results.py
Flow/__init__.py
Logging/Logging.py
Logging/__init__.py
SapGuiFramework-0.1.1.dist-info/LICENSE
SapGuiFramework-0.1.1.dist-info/METADATA
SapGuiFramework-0.1.1.dist-info/WHEEL
SapGuiFramework-0.1.1.dist-info/top_level.txt
SapGuiFramework-0.1.1.dist-info/RECORD
