Metadata-Version: 2.1
Name: SapGuiFramework
Version: 0.1.1
Summary: A Framework Library for controlling the SAP GUI desktop client
Home-page: https://github.com/jduncan8142/SapGuiFramework
Author: Jason Duncan
Author-email: jason.matthew.duncan@gmail.com
Project-URL: Bug Tracker, https://github.com/jduncan8142/SapGuiFramework/issues
Project-URL: Documentation, https://github.com/jduncan8142/SapGuiFramework/wiki
Classifier: Programming Language :: Python :: 3.11
Classifier: Operating System :: Microsoft :: Windows
Classifier: License :: OSI Approved :: MIT License
Requires-Python: >=3.11
License-File: LICENSE
Requires-Dist: pywin32 (>=305)
Requires-Dist: PyYAML (>=6.0)
Provides-Extra: dev
Requires-Dist: pytest (>=7.0) ; extra == 'dev'
Requires-Dist: twine (>=4.0.2) ; extra == 'dev'
